[
    {
        "url": "https://efile.fara.gov/ords/f?p=1381:200:2673194327578::NO:RP,200:P200_REG_NUMBER,P200_DOC_TYPE,P200_COUNTRY:3712,Exhibit%20AB,AFGHANISTAN",
        "state": null,
        "reg_num": "3712",
        "address": "\u00a0\u00a0",
        "foreign_principal": "Embassy of the Islamic Republic of Afghanistan",
        "date": "08/05/1985",
        "registrant": "3712",
        "exhibit_url": "PDF FILE",
        "country": "AFGHANISTAN"
    },
    {
        "url": "https://efile.fara.gov/ords/f?p=1381:200:2673194327578::NO:RP,200:P200_REG_NUMBER,P200_DOC_TYPE,P200_COUNTRY:6065,Exhibit%20AB,AFGHANISTAN",
        "state": "VA",
        "reg_num": "6065",
        "address": "8105 Ainsworth Avenue",
        "foreign_principal": "Transformation and Continuity",
        "date": "09/23/2011",
        "registrant": "6065",
        "exhibit_url": "PDF FILE",
        "country": "AFGHANISTAN"
    },
    {
        "url": "https://efile.fara.gov/ords/f?p=1381:200:2673194327578::NO:RP,200:P200_REG_NUMBER,P200_DOC_TYPE,P200_COUNTRY:2244,Exhibit%20AB,AFGHANISTAN",
        "state": "DC",
        "reg_num": "2244",
        "address": "2341 Wyoming Avenue, NW",
        "foreign_principal": "Embassy of Afghanistan",
        "date": "02/18/1971",
        "registrant": "2244",
        "exhibit_url": "PDF FILE",
        "country": "AFGHANISTAN"
    },
    {
        "url": "https://efile.fara.gov/ords/f?p=1381:200:2673194327578::NO:RP,200:P200_REG_NUMBER,P200_DOC_TYPE,P200_COUNTRY:6685,Exhibit%20AB,ALBANIA",
        "state": null,
        "reg_num": "6685",
        "address": "St. Ismail Qemali, Building 7/1, ap. 10, Tirana 1000\u00a0\u00a0",
        "foreign_principal": "Mr. Enri Ceno, Albania",
        "date": "05/24/2019",
        "registrant": "6685",
        "exhibit_url": "PDF FILE",
        "country": "ALBANIA"
    },
    {
        "url": "https://efile.fara.gov/ords/f?p=1381:200:2673194327578::NO:RP,200:P200_REG_NUMBER,P200_DOC_TYPE,P200_COUNTRY:6399,Exhibit%20AB,ALBANIA",
        "state": null,
        "reg_num": "6399",
        "address": "Bulevardi Zhan'dark 11",
        "foreign_principal": "Democratic Party of Albania",
        "date": "12/11/2016",
        "registrant": "6399",
        "exhibit_url": "PDF FILE",
        "country": "ALBANIA"
    },
    {
        "url": "https://efile.fara.gov/ords/f?p=1381:200:2673194327578::NO:RP,200:P200_REG_NUMBER,P200_DOC_TYPE,P200_COUNTRY:4776,Exhibit%20AB,ALGERIA",
        "state": "DC",
        "reg_num": "4776",
        "address": "2118 Kalorama Road, NW",
        "foreign_principal": "Government of the People's Democratic Republic of Algeria, Embassy",
        "date": "03/02/1993",
        "registrant": "4776",
        "exhibit_url": "PDF FILE",
        "country": "ALGERIA"
    },
    {
        "url": "https://efile.fara.gov/ords/f?p=1381:200:2673194327578::NO:RP,200:P200_REG_NUMBER,P200_DOC_TYPE,P200_COUNTRY:6608,Exhibit%20AB,ALGERIA",
        "state": null,
        "reg_num": "6608",
        "address": "Algiers\u00a0\u00a0",
        "foreign_principal": "People's Democratic Republic of Algeria",
        "date": "11/06/2018",
        "registrant": "6608",
        "exhibit_url": "PDF FILE",
        "country": "ALGERIA"
    },
    {
        "url": "https://efile.fara.gov/ords/f?p=1381:200:2673194327578::NO:RP,200:P200_REG_NUMBER,P200_DOC_TYPE,P200_COUNTRY:6398,Exhibit%20AB,ANGOLA",
        "state": null,
        "reg_num": "6398",
        "address": "\u00a0\u00a0",
        "foreign_principal": "Movimento de Uniao Nacional (M.U.N) Angola",
        "date": "12/01/2016",
        "registrant": "6398",
        "exhibit_url": "PDF FILE",
        "country": "ANGOLA"
    },
    {
        "url": "https://efile.fara.gov/ords/f?p=1381:200:2673194327578::NO:RP,200:P200_REG_NUMBER,P200_DOC_TYPE,P200_COUNTRY:2165,Exhibit%20AB,ANGOLA",
        "state": null,
        "reg_num": "2165",
        "address": "Office of the Presidency of the Republic of Angola",
        "foreign_principal": "Republic of Angola",
        "date": "10/09/1969",
        "registrant": "2165",
        "exhibit_url": "PDF FILE",
        "country": "ANGOLA"
    },
    {
        "url": "https://efile.fara.gov/ords/f?p=1381:200:2673194327578::NO:RP,200:P200_REG_NUMBER,P200_DOC_TYPE,P200_COUNTRY:2987,Exhibit%20AB,ARUBA",
        "state": null,
        "reg_num": "2987",
        "address": "Oranjestad\u00a0\u00a0",
        "foreign_principal": "Government of Aruba",
        "date": "12/29/1978",
        "registrant": "2987",
        "exhibit_url": "PDF FILE",
        "country": "ARUBA"
    },
    {
        "url": "https://efile.fara.gov/ords/f?p=1381:200:2673194327578::NO:RP,200:P200_REG_NUMBER,P200_DOC_TYPE,P200_COUNTRY:6652,Exhibit%20AB,ARUBA",
        "state": null,
        "reg_num": "6652",
        "address": "LG. Smith Blvd. 9 - P.O. Box 1019",
        "foreign_principal": "Aruba Tourism Authority (ATA)",
        "date": "03/18/2019",
        "registrant": "6652",
        "exhibit_url": "PDF FILE",
        "country": "ARUBA"
    },
    {
        "url": "https://efile.fara.gov/ords/f?p=1381:200:2673194327578::NO:RP,200:P200_REG_NUMBER,P200_DOC_TYPE,P200_COUNTRY:6549,Exhibit%20AB,AUSTRALIA",
        "state": null,
        "reg_num": "6549",
        "address": "Level 1, Alice Plaza",
        "foreign_principal": "Tourism Northern Territory",
        "date": "04/30/2018",
        "registrant": "6549",
        "exhibit_url": "PDF FILE",
        "country": "AUSTRALIA"
    },
    {
        "url": "https://efile.fara.gov/ords/f?p=1381:200:2673194327578::NO:RP,200:P200_REG_NUMBER,P200_DOC_TYPE,P200_COUNTRY:4450,Exhibit%20AB,AUSTRALIA",
        "state": null,
        "reg_num": "4450",
        "address": "Sydney\u00a0\u00a0",
        "foreign_principal": "New South Wales Tourism Commission (Government of New South Wales)",
        "date": "12/18/1990",
        "registrant": "4450",
        "exhibit_url": "PDF FILE",
        "country": "AUSTRALIA"
    },
    {
        "url": "https://efile.fara.gov/ords/f?p=1381:200:2673194327578::NO:RP,200:P200_REG_NUMBER,P200_DOC_TYPE,P200_COUNTRY:3634,Exhibit%20AB,AUSTRALIA",
        "state": null,
        "reg_num": "3634",
        "address": "80 Birdwood Parade",
        "foreign_principal": "Minderoo Foundation Pty Ltd.",
        "date": "11/15/1984",
        "registrant": "3634",
        "exhibit_url": "PDF FILE",
        "country": "AUSTRALIA"
    },
    {
        "url": "https://efile.fara.gov/ords/f?p=1381:200:2673194327578::NO:RP,200:P200_REG_NUMBER,P200_DOC_TYPE,P200_COUNTRY:6549,Exhibit%20AB,AUSTRALIA",
        "state": null,
        "reg_num": "6549",
        "address": "Collins Square Tower Two, Level 28, 727 Collins St",
        "foreign_principal": "Melbourne Convention & Visitors Bureau",
        "date": "04/30/2018",
        "registrant": "6549",
        "exhibit_url": "PDF FILE",
        "country": "AUSTRALIA"
    }
]